fourier_accountant/__init__.py
fourier_accountant/common.py
fourier_accountant/compute_delta.py
fourier_accountant/compute_delta_var.py
fourier_accountant/compute_eps.py
fourier_accountant/compute_eps_var.py
fourier_accountant/experimental/__init__.py
fourier_accountant/experimental/binomial_mechanism.py
fourier_accountant/experimental/exponential_mechanism.py
fourier_accountant/experimental/subsampled_gaussian_bounds.py
fourier_accountant-0.12.11.dist-info/LICENSE
fourier_accountant-0.12.11.dist-info/METADATA
fourier_accountant-0.12.11.dist-info/WHEEL
fourier_accountant-0.12.11.dist-info/top_level.txt
fourier_accountant-0.12.11.dist-info/RECORD
